{
  "agent": {
    "name": "Kit",
    "emoji": "🦊",
    "status": "online",
    "statusText": "Watching over things"
  },
  "lastSync": "2026-02-09T18:54:31.462Z",
  "notionUrl": "https://www.notion.so/be60b425a2ad40099338723024c839fd",
  "tasks": {
    "todo": [],
    "inProgress": [],
    "done": [],
    "archived": []
  },
  "scheduledJobs": [
    {
      "name": "overnight-build",
      "schedule": {
        "kind": "cron",
        "expr": "0 23 * * *",
        "tz": "America/Vancouver"
      },
      "description": ""
    },
    {
      "name": "build-accountability",
      "schedule": {
        "kind": "cron",
        "expr": "0 4 * * *",
        "tz": "America/Vancouver"
      },
      "description": ""
    },
    {
      "name": "morning-briefing",
      "schedule": {
        "kind": "cron",
        "expr": "30 4 * * *",
        "tz": "America/Vancouver"
      },
      "description": ""
    },
    {
      "name": "clawdbot-update-audit",
      "schedule": {
        "kind": "cron",
        "expr": "0 9 * * *",
        "tz": "America/Vancouver"
      },
      "description": ""
    },
    {
      "name": "x-daily-briefing",
      "schedule": {
        "kind": "cron",
        "expr": "0 9 * * *",
        "tz": "America/Vancouver"
      },
      "description": ""
    }
  ],
  "actionLog": [
    {
      "time": "2026-02-09T10:49:29-08:00",
      "action": "📊 Auto-update dashboard data",
      "source": "git"
    },
    {
      "time": "2026-02-09T10:49:27-08:00",
      "action": "📊 Update GitHub activity",
      "source": "git"
    },
    {
      "time": "2026-02-09T10:44:13-08:00",
      "action": "📊 Auto-update dashboard data",
      "source": "git"
    },
    {
      "time": "2026-02-09T10:44:12-08:00",
      "action": "📊 Update GitHub activity",
      "source": "git"
    },
    {
      "time": "2026-02-09T10:38:54-08:00",
      "action": "📊 Auto-update dashboard data",
      "source": "git"
    }
  ],
  "notes": [
    "Check kit@adriancrook.com for urgent emails",
    "Check Instagram @adriancrookinc DMs",
    "Draft approval required for ALL external messages",
    "Self-merge PRs on my repos (don't wait for approval)",
    "Tesla search runs daily at 10am Pacific"
  ]
}
